[
  {
    "full_name": "zutrinken/bleak",
    "stargazers_count": 517,
    "open_issues_count": 12,
    "forks_count": 139
  },
  {
    "full_name": "pmndrs/react-spring",
    "stargazers_count": 22015,
    "open_issues_count": 47,
    "forks_count": 959
  },
  {
    "full_name": "rainbow-me/rainbow",
    "stargazers_count": 2024,
    "open_issues_count": 32,
    "forks_count": 271
  },
  {
    "full_name": "chakra-ui/chakra-ui",
    "stargazers_count": 22972,
    "open_issues_count": 117,
    "forks_count": 1997
  },
  {
    "full_name": "Aarif123456/KeystrokeDynamicsSpoofer",
    "stargazers_count": 8,
    "open_issues_count": 0,
    "forks_count": 1
  },
  {
    "full_name": "boorje/react-news-app",
    "stargazers_count": 2,
    "open_issues_count": 13,
    "forks_count": 4
  },
  {
    "full_name": "benawad/fullstack-graphql-airbnb-clone",
    "stargazers_count": 1431,
    "open_issues_count": 23,
    "forks_count": 413
  },
  {
    "full_name": "negomi/react-burger-menu",
    "stargazers_count": 4552,
    "open_issues_count": 5,
    "forks_count": 566
  },
  {
    "full_name": "EugeCos/stylish-sidebar",
    "stargazers_count": 8,
    "open_issues_count": 0,
    "forks_count": 6
  },
  {
    "full_name": "NyashaNziramasanga/facebook-navbar-ui-clone",
    "stargazers_count": 1,
    "open_issues_count": 2,
    "forks_count": 1
  },
  {
    "full_name": "Abhirup-99/DesktopWallpaper",
    "stargazers_count": 1,
    "open_issues_count": 0,
    "forks_count": 2
  },
  {
    "full_name": "davidhu2000/react-spinners",
    "stargazers_count": 2058,
    "open_issues_count": 25,
    "forks_count": 178
  },
  {
    "full_name": "microsoft/cascadia-code",
    "stargazers_count": 18778,
    "open_issues_count": 64,
    "forks_count": 625
  },
  {
    "full_name": "google/android-emulator-hypervisor-driver-for-amd-processors",
    "stargazers_count": 406,
    "open_issues_count": 39,
    "forks_count": 150
  },
  {
    "full_name": "kiruba-r11/file-categorizer",
    "stargazers_count": 2,
    "open_issues_count": 0,
    "forks_count": 1
  },
  {
    "full_name": "tschaub/gh-pages",
    "stargazers_count": 2698,
    "open_issues_count": 101,
    "forks_count": 176
  },
  {
    "full_name": "0xPolygon/polygon-sdk",
    "stargazers_count": 417,
    "open_issues_count": 25,
    "forks_count": 90
  },
  {
    "full_name": "hunterbecton/react-firebase-passwordless",
    "stargazers_count": 14,
    "open_issues_count": 1,
    "forks_count": 8
  },
  {
    "full_name": "CodeFlow201/GitMarkonics",
    "stargazers_count": 33,
    "open_issues_count": 16,
    "forks_count": 46
  },
  {
    "full_name": "WazirX/wazirx-api",
    "stargazers_count": 191,
    "open_issues_count": 29,
    "forks_count": 42
  },
  {
    "full_name": "30-seconds/30-seconds-of-code",
    "stargazers_count": 90512,
    "open_issues_count": 6,
    "forks_count": 9566
  },
  {
    "full_name": "ConsenSys/Tokens",
    "stargazers_count": 1582,
    "open_issues_count": 21,
    "forks_count": 1067
  },
  {
    "full_name": "Priyanshu-CODERX/Fake-News-Classifier",
    "stargazers_count": 1,
    "open_issues_count": 0,
    "forks_count": 1
  },
  {
    "full_name": "hugo-toha/toha",
    "stargazers_count": 435,
    "open_issues_count": 40,
    "forks_count": 309
  },
  {
    "full_name": "CRED-CLUB/synth-android",
    "stargazers_count": 783,
    "open_issues_count": 5,
    "forks_count": 78
  },
  {
    "full_name": "education/GitHubGraduation-2021",
    "stargazers_count": 1405,
    "open_issues_count": 1346,
    "forks_count": 7900
  },
  {
    "full_name": "An-prog-hub/covidstar",
    "stargazers_count": 3,
    "open_issues_count": 0,
    "forks_count": 2
  },
  {
    "full_name": "gatsbyjs/store.gatsbyjs.org",
    "stargazers_count": 568,
    "open_issues_count": 27,
    "forks_count": 220
  },
  {
    "full_name": "An-prog-hub/human-pose-estimation",
    "stargazers_count": 1,
    "open_issues_count": 0,
    "forks_count": 0
  },
  {
    "full_name": "torvalds/linux",
    "stargazers_count": 123434,
    "open_issues_count": 323,
    "forks_count": 40450
  }
]